README.rst
grin.py
setup.cfg
setup.py
grin.egg-info/PKG-INFO
grin.egg-info/SOURCES.txt
grin.egg-info/dependency_links.txt
grin.egg-info/entry_points.txt
grin.egg-info/top_level.txt