Metadata-Version: 1.2
Name: grin
Version: 1.3.0
Summary: A grep program configured the way I like it.
Home-page: https://github.com/matthew-brett/grin
Author: Robert Kern
Author-email: robert.kern@enthought.com
Maintainer: Matthew Brett
Maintainer-email: matthew.brett@gmail.com
License: BSD
Platform: UNKNOWN
Classifier: License :: OSI Approved :: BSD License
Classifier: Development Status :: 5 - Production/Stable
Classifier: Environment :: Console
Classifier: Intended Audience :: Developers
Classifier: Operating System :: OS Independent
Classifier: Programming Language :: Python
Classifier: Programming Language :: Python :: 3
Classifier: Topic :: Utilities
